setup.py
hulkbuster/__init__.py
hulkbuster.egg-info/PKG-INFO
hulkbuster.egg-info/SOURCES.txt
hulkbuster.egg-info/dependency_links.txt
hulkbuster.egg-info/not-zip-safe
hulkbuster.egg-info/requires.txt
hulkbuster.egg-info/top_level.txt