Metadata-Version: 1.0
Name: hulkbuster
Version: 0.4
Summary: IITBombayX EDX API
Home-page: https://github.com/DhruvThakker/hulkbuster
Author: HulkBuster441
Author-email: dthakker1997@gmail.com
License: MIT
Platform: UNKNOWN
